mozparsers/__init__.py
mozparsers/parse_events.py
mozparsers/parse_histograms.py
mozparsers/parse_scalars.py
mozparsers/shared_telemetry_utils.py
mozparsers-1.0.0.dist-info/DESCRIPTION.rst
mozparsers-1.0.0.dist-info/METADATA
mozparsers-1.0.0.dist-info/RECORD
mozparsers-1.0.0.dist-info/WHEEL
mozparsers-1.0.0.dist-info/metadata.json
mozparsers-1.0.0.dist-info/top_level.txt
