Metadata-Version: 2.0
Name: mozparsers
Version: 1.0.0
Summary: Shared parsers for the Telemetry probe regitries.
Home-page: https://firefox-source-docs.mozilla.org/toolkit/components/telemetry/telemetry/collection/index.html
Author: Mozilla Telemetry Team
Author-email: telemetry-client-dev@mozilla.com
License: MPL 2.0
Keywords: mozilla,telemetry,parsers
Platform: UNKNOWN
Classifier: Topic :: Software Development :: Build Tools
Classifier: License :: OSI Approved :: Mozilla Public License 2.0 (MPL 2.0)
Classifier: Programming Language :: Python :: 2.7
